dmi/__init__.py
dmi/eval.py
dmi/gui.py
dmi/version.py
dmi/.dbs/m4.sqlite
dmi/.dbs/m4c.sqlite
dmi/.dbs/m5.sqlite
dmi/modules/__init__.py
dmi/modules/dd.py
dmi/modules/m5.py
dmi-0.0.1.9.dist-info/METADATA
dmi-0.0.1.9.dist-info/WHEEL
dmi-0.0.1.9.dist-info/top_level.txt
dmi-0.0.1.9.dist-info/RECORD
