Metadata-Version: 2.1
Name: dmi
Version: 0.0.1.9
Summary: An interactive question application
Home-page: https://github.com/chapmanbe/dminteract
Author: Brian Chapman
Author-email: chapmanbe@gmail.com
License: MIT
Platform: UNKNOWN
Requires-Python: >=3.8
Requires-Dist: ipywidgets
